LICENSE
MANIFEST.in
README.md
setup.py
apitools/__init__.py
apitools/backbonemodelgenerator.py
apitools/datagenerator.py
apitools/flasksqlalchemymodelgenerator.py
apitools/invaliddatagenerator.py
apitools/modelgenerator.py
apitools/resourceserver.py
apitools/schemasstore.py
apitools/urlgenerator.py
apitools/utils.py
apitools/validation.py
apitools.egg-info/PKG-INFO
apitools.egg-info/SOURCES.txt
apitools.egg-info/dependency_links.txt
apitools.egg-info/top_level.txt