Metadata-Version: 1.0
Name: apitools
Version: 0.1.4
Summary: Tools to play with json-schema and rest apis
Home-page: https://github.com/hamstah/apitools
Author: Nicolas Esteves
Author-email: hamstahguru@gmail.com
License: MIT
Platform: UNKNOWN
